{
  "vipHeaderBgImage" : {
    "url_dark" : "https://h5.sinaimg.cn/upload/100/1734/2022/06/01/headerimage_dark.png",
    "url1" : "https://h5.sinaimg.cn/upload/100/1734/2022/06/01/huxingxiafang_default.png",
    "url" : "https://h5.sinaimg.cn/upload/100/1734/2022/06/01/headerimage_default.png",
    "url1_dark" : "https://h5.sinaimg.cn/upload/100/1734/2022/06/01/huxingxiafang_dark.png"
  },
  "pageData" : {
    "style" : {
      "column" : 2,
      "hGap" : "10",
      "vGap" : "10",
      "flowType" : "staggered"
    },
    "flowBusinessType" : "business",
    "pageDataType" : "flow",
    "flowId" : "profile_me",
    "title" : "个人主页",
    "businessId" : "mine"
  },
  "config" : {
    "paging" : {
      "threshold" : 100
    }
  },
  "moreInfo" : {
    "params" : {
      "sinceId" : "skip_3934103603"
    },
    "noMore" : false
  },
  "items" : [
    {
      "itemId" : "profileme_mine",
      "style" : {
        "padding" : [
          10,
          0,
          10,
          0
        ],
        "column" : 4
      },
      "items" : [
        {
          "category" : "cell",
          "style" : {
            "grid" : true,
            "height" : 67
          },
          "content" : {
            "type" : "text",
            "style" : {
              "textColor" : "#939393",
              "textColorKey" : "CommonGray93",
              "textSize" : 12,
              "gravity" : "center",
              "margin" : [
                0,
                4,
                0,
                0
              ]
            },
            "content" : "微博"
          },
          "itemId" : "mainnums_statuses",
          "title" : {
            "type" : "text",
            "style" : {
              "textColor" : "#333333",
              "bold" : true,
              "textColorKey" : "CommonGray33",
              "textSize" : 16,
              "margin" : [
                0,
                16,
                0,
                0
              ],
              "gravity" : "center"
            },
            "content" : "606"
          },
          "type" : "iconInfo",
          "click" : {
            "type" : "group",
            "modules" : [
              {
                "type" : "scheme",
                "scheme" : "sinaweibo://cardlist?containerid=2304133934103603_-_WEIBO_SECOND_PROFILE_WEIBO&apipath=/2/profile/statuses/tab",
                "actionlog" : {
                  "ext" : "moduleId:mainnums_statuses|itemId:mainnums_statuses",
                  "fid" : "profile_me",
                  "act_code" : 2264,
                  "cardid" : "mainnums_statuses"
                }
              }
            ],
            "executeType" : "depend"
          }
        },
        {
          "category" : "cell",
          "style" : {
            "grid" : true,
            "height" : 67
          },
          "content" : {
            "type" : "text",
            "style" : {
              "textColor" : "#939393",
              "textColorKey" : "CommonGray93",
              "textSize" : 12,
              "gravity" : "center",
              "margin" : [
                0,
                4,
                0,
                0
              ]
            },
            "content" : "视频"
          },
          "itemId" : "mainnums_video_status",
          "title" : {
            "type" : "text",
            "style" : {
              "textColor" : "#333333",
              "bold" : true,
              "textColorKey" : "CommonGray33",
              "textSize" : 16,
              "margin" : [
                0,
                16,
                0,
                0
              ],
              "gravity" : "center"
            },
            "content" : "4"
          },
          "type" : "iconInfo",
          "click" : {
            "type" : "group",
            "modules" : [
              {
                "type" : "scheme",
                "scheme" : "sinaweibo://userinfo?uid=3934103603&selected_tab_type=video&extparam=tabminivideo&is_top=1",
                "actionlog" : {
                  "ext" : "moduleId:mainnums_video_status|itemId:mainnums_video_status",
                  "fid" : "profile_me",
                  "act_code" : 2264,
                  "cardid" : "mainnums_video_status"
                }
              }
            ],
            "executeType" : "depend"
          }
        },
        {
          "category" : "cell",
          "style" : {
            "grid" : true,
            "height" : 67
          },
          "content" : {
            "type" : "text",
            "style" : {
              "textColor" : "#939393",
              "textColorKey" : "CommonGray93",
              "textSize" : 12,
              "gravity" : "center",
              "margin" : [
                0,
                4,
                0,
                0
              ]
            },
            "content" : "关注"
          },
          "itemId" : "mainnums_friends",
          "title" : {
            "type" : "text",
            "style" : {
              "textColor" : "#333333",
              "bold" : true,
              "textColorKey" : "CommonGray33",
              "textSize" : 16,
              "margin" : [
                0,
                16,
                0,
                0
              ],
              "gravity" : "center"
            },
            "content" : "59"
          },
          "type" : "iconInfo",
          "click" : {
            "type" : "group",
            "modules" : [
              {
                "type" : "scheme",
                "scheme" : "sinaweibo://cardlist?containerid=231093_-_selffollowed",
                "actionlog" : {
                  "ext" : "moduleId:mainnums_friends|itemId:mainnums_friends",
                  "fid" : "profile_me",
                  "act_code" : 2264,
                  "cardid" : "mainnums_friends"
                }
              },
              {
                "type" : "dot",
                "unreadKey" : "me_follow_updateremind"
              }
            ],
            "executeType" : "depend"
          },
          "titleDot" : {
            "active" : false,
            "style" : {
              "margin" : [
                0,
                0,
                10,
                0
              ],
              "height" : 0,
              "textColorKey" : "CommonButtonText",
              "width" : 0,
              "textSize" : 10,
              "dotColor" : "#F43530",
              "dotColorKey" : "UserProfileCardManagementColor",
              "textColor" : "#FFFFFF"
            },
            "unreadKey" : "me_follow_updateremind",
            "inactiveType" : "none",
            "dotText" : "",
            "type" : "dot",
            "activeType" : "dot",
            "dotSource" : "unread"
          }
        },
        {
          "category" : "cell",
          "style" : {
            "grid" : true,
            "height" : 67
          },
          "content" : {
            "type" : "text",
            "style" : {
              "textColor" : "#939393",
              "textColorKey" : "CommonGray93",
              "textSize" : 12,
              "gravity" : "center",
              "margin" : [
                0,
                4,
                0,
                0
              ]
            },
            "content" : "粉丝"
          },
          "itemId" : "mainnums_followers",
          "title" : {
            "type" : "text",
            "style" : {
              "textColor" : "#333333",
              "bold" : true,
              "textColorKey" : "CommonGray33",
              "textSize" : 16,
              "margin" : [
                0,
                16,
                0,
                0
              ],
              "gravity" : "center"
            },
            "content" : "172"
          },
          "type" : "iconInfo",
          "click" : {
            "type" : "group",
            "modules" : [
              {
                "type" : "scheme",
                "scheme" : "sinaweibo://cardlist?containerid=231016",
                "actionlog" : {
                  "ext" : "moduleId:mainnums_followers|itemId:mainnums_followers",
                  "fid" : "profile_me",
                  "act_code" : 2264,
                  "cardid" : "mainnums_followers"
                }
              },
              {
                "type" : "dot",
                "unreadKey" : "follower"
              }
            ],
            "executeType" : "depend"
          },
          "titleDot" : {
            "active" : false,
            "style" : {
              "margin" : [
                0,
                0,
                10,
                0
              ],
              "height" : 0,
              "textColorKey" : "CommonButtonText",
              "width" : 0,
              "textSize" : 10,
              "dotColor" : "#F43530",
              "dotColorKey" : "UserProfileCardManagementColor",
              "textColor" : "#FFFFFF"
            },
            "unreadKey" : "follower",
            "inactiveType" : "none",
            "dotText" : "",
            "type" : "dot",
            "activeType" : "dot",
            "dotSource" : "unread"
          }
        }
      ],
      "type" : "grid",
      "category" : "group",
      "header" : {
        "category" : "mine",
        "style" : {
          "padding" : [
            0,
            0,
            0,
            0
          ]
        },
        "itemId" : "profileme_mine_head",
        "avatar" : {
          "itemId" : "profileme_head_avatar",
          "style" : {
            "pendantHiddenInDark" : true,
            "radius" : 5.9000000000000004,
            "vIconWidth" : 16,
            "pendantOffsetY" : -5.5,
            "width" : 59,
            "pendantWidth" : 65,
            "pendantGifScrollNotNeedRePlay" : true,
            "mask_type" : 0,
            "pendantHeight" : 70,
            "pendantGifLoopCount" : 1,
            "height" : 59,
            "pendantOffsetX" : 0,
            "pendantStopAtLastFrame" : true
          },
          "badgeUrl" : "",
          "mask_type" : 0,
          "pendantUrl" : "https://h5.sinaimg.cn/upload/108/1793/2022/07/12/lijinewr.gif",
          "avatarUrl" : "https://tvax4.sinaimg.cn/crop.0.0.1080.1080.180/ea7da833ly8h7vyyjn5v6j20u00u0tcy.jpg?KID=imgbed,tva&Expires=1684229832&ssig=gcNchj3eHL",
          "type" : "avatar",
          "click" : {
            "executeType" : "depend",
            "type" : "group",
            "params" : {
              "needRefresh" : true
            },
            "modules" : [
              {
                "actionlog" : {
                  "ext" : "moduleId:profileme_mine|itemId:profileme_head_avatar",
                  "fid" : "profile_me",
                  "act_code" : 2264,
                  "cardid" : "profileme_mine"
                },
                "type" : "scheme",
                "scheme" : "sinaweibo://userinfo?uid=3934103603&fid=profile_me",
                "params" : {
                  "needRefresh" : true
                }
              }
            ]
          }
        },
        "username" : {
          "itemId" : "profileme_head_username",
          "style" : {
            "maxLines" : 1,
            "margin" : [
              12,
              7,
              0,
              0
            ],
            "textColorKey" : "CommonGray33",
            "textSize" : 18,
            "ellipsize" : "end",
            "textColor" : "#333333",
            "bold" : true
          },
          "content" : "废话GPT",
          "type" : "text",
          "click" : {
            "executeType" : "depend",
            "type" : "group",
            "params" : {
              "needRefresh" : true
            },
            "modules" : [
              {
                "actionlog" : {
                  "ext" : "moduleId:profileme_mine|itemId:profileme_head_username",
                  "fid" : "profile_me",
                  "act_code" : 2264,
                  "cardid" : "profileme_mine"
                },
                "type" : "scheme",
                "scheme" : "sinaweibo://userinfo?uid=3934103603&fid=profile_me",
                "params" : {
                  "needRefresh" : true
                }
              }
            ]
          }
        },
        "vipCenter" : {
          "title" : {
            "type" : "text",
            "style" : {
              "textColor" : "#ff8226",
              "textColorKey" : "CommonYellow",
              "ellipsize" : "end",
              "maxLines" : 1,
              "textSize" : 12
            },
            "content" : "会员"
          },
          "icon" : {
            "type" : "icon",
            "style" : {
              "darkMode" : "urlAppend",
              "width" : 30,
              "height" : 30,
              "margin" : [
                0,
                0,
                3,
                0
              ]
            },
            "iconUrl" : "https://h5.sinaimg.cn/upload/1071/1468/2021/09/07/hy_dongtu.gif"
          },
          "content" : {
            "itemId" : "profile_me_vipcenter",
            "type" : "richText",
            "click" : {
              "executeType" : "depend",
              "type" : "group",
              "params" : {
                "needRefresh" : true
              },
              "modules" : [
                {
                  "actionlog" : {
                    "ext" : "moduleId:profileme_mine|itemId:profile_me_vipcenter",
                    "fid" : "profile_me",
                    "act_code" : 2264,
                    "cardid" : "profileme_mine"
                  },
                  "type" : "scheme",
                  "scheme" : "sinaweibo://userinfo?uid=3934103603&fid=profile_me",
                  "params" : {
                    "needRefresh" : true
                  }
                }
              ]
            },
            "contents" : [
              {
                "type" : "icon",
                "style" : {
                  "width" : 30,
                  "darkMode" : "alpha",
                  "height" : 30
                },
                "iconUrl" : "https://h5.sinaimg.cn/upload/108/1284/2020/11/12/hyicon-as.png"
              },
              {
                "type" : "icon",
                "style" : {
                  "width" : 3,
                  "height" : 30
                },
                "iconUrl" : ""
              },
              {
                "type" : "text",
                "style" : {
                  "textColorKey" : "CommonYellow",
                  "textSize" : 12,
                  "textColor" : "#ff8226"
                },
                "content" : "会员"
              }
            ]
          }
        },
        "type" : "header",
        "click" : {
          "executeType" : "depend",
          "type" : "group",
          "params" : {
            "needRefresh" : true
          },
          "modules" : [
            {
              "actionlog" : {
                "ext" : "moduleId:profileme_mine|itemId:profile_me_vipcenter",
                "fid" : "profile_me",
                "act_code" : 2264,
                "cardid" : "profileme_mine"
              },
              "type" : "scheme",
              "scheme" : "sinaweibo://userinfo?uid=3934103603&fid=profile_me",
              "params" : {
                "needRefresh" : true
              }
            }
          ]
        },
        "desc" : {
          "itemId" : "profileme_head_desc",
          "style" : {
            "textColor" : "#939393",
            "textColorKey" : "CommonGray93",
            "ellipsize" : "end",
            "maxLines" : 1,
            "textSize" : 12,
            "margin" : [
              12,
              10,
              10,
              10
            ]
          },
          "content" : "简介：暂无简介",
          "type" : "text",
          "click" : {
            "executeType" : "depend",
            "type" : "group",
            "params" : {
              "needRefresh" : true
            },
            "modules" : [
              {
                "actionlog" : {
                  "ext" : "moduleId:profileme_mine|itemId:profileme_head_desc",
                  "fid" : "profile_me",
                  "act_code" : 2264,
                  "cardid" : "profileme_mine"
                },
                "type" : "scheme",
                "scheme" : "sinaweibo://userinfo?uid=3934103603&fid=profile_me",
                "params" : {
                  "needRefresh" : true
                }
              }
            ]
          }
        },
        "vipView" : null
      }
    },
    {
      "canEdit" : "0",
      "itemId" : "100505_-_top8",
      "style" : {
        "padding" : [
          0,
          0,
          0,
          7
        ],
        "column" : 4,
        "margin" : [
          10,
          0,
          10,
          0
        ],
        "background" : {
          "corners" : [
            7,
            7,
            7,
            7
          ],
          "colorKey" : "CommonCardBackground",
          "type" : "color",
          "image" : "image",
          "color" : "#FFFFFF"
        }
      },
      "items" : [
        {
          "category" : "cell",
          "style" : {
            "margin" : [
              0,
              0,
              0,
              0
            ],
            "grid" : true,
            "height" : 82
          },
          "content" : {
            "style" : {
              "margin" : [
                0,
                6,
                0,
                0
              ],
              "textColorKey" : "CommonGray33",
              "gravity" : "center",
              "textSize" : 12,
              "ellipsize" : "end",
              "textColor" : "#333333",
              "maxLines" : 1
            },
            "content" : "我的相册",
            "type" : "text"
          },
          "itemId" : "100505_-_album",
          "image" : {
            "style" : {
              "darkMode" : "urlAppend",
              "height" : 36,
              "width" : 36,
              "margin" : [
                0,
                15,
                0,
                0
              ]
            },
            "iconUrl" : "https://h5.sinaimg.cn/upload/100/888/2021/04/01/album.png",
            "type" : "icon"
          },
          "type" : "iconInfo",
          "click" : {
            "type" : "group",
            "modules" : [
              {
                "type" : "scheme",
                "scheme" : "sinaweibo://cardlist?containerid=2318263934103603_-_mobile_profile_album_-_index",
                "actionlog" : {
                  "ext" : "moduleId:100505_-_top8|itemId:100505_-_album",
                  "fid" : "profile_me",
                  "act_code" : 2265,
                  "cardid" : "100505_-_top8"
                }
              },
              {
                "type" : "dot",
                "unreadKey" : "album"
              }
            ],
            "executeType" : "depend"
          },
          "dot" : {
            "active" : false,
            "style" : {
              "margin" : [
                0,
                0,
                10,
                0
              ],
              "height" : 0,
              "textColorKey" : "CommonButtonText",
              "width" : 0,
              "textSize" : 10,
              "dotColor" : "#F43530",
              "dotColorKey" : "UserProfileCardManagementColor",
              "textColor" : "#FFFFFF"
            },
            "unreadKey" : "album",
            "inactiveType" : "none",
            "dotText" : "",
            "type" : "dot",
            "activeType" : "dot",
            "dotSource" : "unread"
          }
        },
        {
          "category" : "cell",
          "style" : {
            "margin" : [
              0,
              0,
              0,
              0
            ],
            "grid" : true,
            "height" : 82
          },
          "content" : {
            "style" : {
              "margin" : [
                0,
                6,
                0,
                0
              ],
              "textColorKey" : "CommonGray33",
              "gravity" : "center",
              "textSize" : 12,
              "ellipsize" : "end",
              "textColor" : "#333333",
              "maxLines" : 1
            },
            "content" : "赞/收藏",
            "type" : "text"
          },
          "itemId" : "100505_-_like",
          "image" : {
            "style" : {
              "darkMode" : "urlAppend",
              "height" : 36,
              "width" : 36,
              "margin" : [
                0,
                15,
                0,
                0
              ]
            },
            "iconUrl" : "https://h5.sinaimg.cn/upload/100/888/2021/04/01/like.png",
            "type" : "icon"
          },
          "type" : "iconInfo",
          "click" : {
            "type" : "group",
            "modules" : [
              {
                "type" : "scheme",
                "scheme" : "sinaweibo://cardlist?containerid=2308693934103603_-_mix",
                "actionlog" : {
                  "ext" : "moduleId:100505_-_top8|itemId:100505_-_like",
                  "fid" : "profile_me",
                  "act_code" : 2265,
                  "cardid" : "100505_-_top8"
                }
              },
              {
                "type" : "dot",
                "unreadKey" : "like"
              }
            ],
            "executeType" : "depend"
          },
          "dot" : {
            "active" : false,
            "style" : {
              "margin" : [
                0,
                0,
                10,
                0
              ],
              "height" : 0,
              "textColorKey" : "CommonButtonText",
              "width" : 0,
              "textSize" : 10,
              "dotColor" : "#F43530",
              "dotColorKey" : "UserProfileCardManagementColor",
              "textColor" : "#FFFFFF"
            },
            "unreadKey" : "like",
            "inactiveType" : "none",
            "dotText" : "",
            "type" : "dot",
            "activeType" : "dot",
            "dotSource" : "unread"
          }
        },
        {
          "category" : "cell",
          "style" : {
            "margin" : [
              0,
              0,
              0,
              0
            ],
            "grid" : true,
            "height" : 82
          },
          "content" : {
            "style" : {
              "margin" : [
                0,
                6,
                0,
                0
              ],
              "textColorKey" : "CommonGray33",
              "gravity" : "center",
              "textSize" : 12,
              "ellipsize" : "end",
              "textColor" : "#333333",
              "maxLines" : 1
            },
            "content" : "浏览记录",
            "type" : "text"
          },
          "itemId" : "100505_-_watchhistory",
          "image" : {
            "style" : {
              "darkMode" : "urlAppend",
              "height" : 36,
              "width" : 36,
              "margin" : [
                0,
                15,
                0,
                0
              ]
            },
            "iconUrl" : "https://h5.sinaimg.cn/upload/100/888/2021/04/01/watchhistory.png",
            "type" : "icon"
          },
          "type" : "iconInfo",
          "click" : {
            "type" : "group",
            "modules" : [
              {
                "type" : "scheme",
                "scheme" : "sinaweibo://wbox?id=2cms4p0vqx&uid=3934103603&type=1",
                "actionlog" : {
                  "ext" : "moduleId:100505_-_top8|itemId:100505_-_watchhistory",
                  "fid" : "profile_me",
                  "act_code" : 2265,
                  "cardid" : "100505_-_top8"
                }
              }
            ],
            "executeType" : "depend"
          }
        },
        {
          "category" : "cell",
          "style" : {
            "margin" : [
              0,
              0,
              0,
              0
            ],
            "grid" : true,
            "height" : 82
          },
          "content" : {
            "style" : {
              "margin" : [
                0,
                6,
                0,
                0
              ],
              "textColorKey" : "CommonGray33",
              "gravity" : "center",
              "textSize" : 12,
              "ellipsize" : "end",
              "textColor" : "#333333",
              "maxLines" : 1
            },
            "content" : "草稿箱",
            "type" : "text"
          },
          "itemId" : "100505_-_draft",
          "image" : {
            "style" : {
              "darkMode" : "urlAppend",
              "height" : 36,
              "width" : 36,
              "margin" : [
                0,
                15,
                0,
                0
              ]
            },
            "iconUrl" : "https://h5.sinaimg.cn/upload/100/888/2021/04/01/draft.png",
            "type" : "icon"
          },
          "type" : "iconInfo",
          "click" : {
            "type" : "group",
            "modules" : [
              {
                "type" : "scheme",
                "scheme" : "sinaweibo://draftbox",
                "actionlog" : {
                  "ext" : "moduleId:100505_-_top8|itemId:100505_-_draft",
                  "fid" : "profile_me",
                  "act_code" : 2265,
                  "cardid" : "100505_-_top8"
                }
              }
            ],
            "executeType" : "depend"
          }
        },
        {
          "category" : "cell",
          "style" : {
            "margin" : [
              0,
              0,
              0,
              0
            ],
            "grid" : true,
            "height" : 82
          },
          "content" : {
            "style" : {
              "margin" : [
                0,
                6,
                0,
                0
              ],
              "textColorKey" : "CommonGray33",
              "gravity" : "center",
              "textSize" : 12,
              "ellipsize" : "end",
              "textColor" : "#333333",
              "maxLines" : 1
            },
            "content" : "我的钱包",
            "type" : "text"
          },
          "itemId" : "100505_-_pay",
          "image" : {
            "style" : {
              "darkMode" : "urlAppend",
              "height" : 36,
              "width" : 36,
              "margin" : [
                0,
                15,
                0,
                0
              ]
            },
            "iconUrl" : "https://h5.sinaimg.cn/upload/100/888/2021/04/01/pay.png",
            "type" : "icon"
          },
          "type" : "iconInfo",
          "click" : {
            "type" : "group",
            "modules" : [
              {
                "type" : "scheme",
                "scheme" : "https://pay.sc.weibo.com/pay/index?src=me",
                "actionlog" : {
                  "ext" : "moduleId:100505_-_top8|itemId:100505_-_pay",
                  "fid" : "profile_me",
                  "act_code" : 2265,
                  "cardid" : "100505_-_top8"
                }
              },
              {
                "type" : "dot",
                "unreadKey" : "payment"
              }
            ],
            "executeType" : "depend"
          },
          "dot" : {
            "active" : false,
            "style" : {
              "margin" : [
                0,
                0,
                10,
                0
              ],
              "height" : 0,
              "textColorKey" : "CommonButtonText",
              "width" : 0,
              "textSize" : 10,
              "dotColor" : "#F43530",
              "dotColorKey" : "UserProfileCardManagementColor",
              "textColor" : "#FFFFFF"
            },
            "unreadKey" : "payment",
            "inactiveType" : "none",
            "dotText" : "",
            "type" : "dot",
            "activeType" : "dot",
            "dotSource" : "unread"
          }
        },
        {
          "category" : "cell",
          "style" : {
            "margin" : [
              0,
              0,
              0,
              0
            ],
            "grid" : true,
            "height" : 82
          },
          "content" : {
            "style" : {
              "margin" : [
                0,
                6,
                0,
                0
              ],
              "textColorKey" : "CommonGray33",
              "gravity" : "center",
              "textSize" : 12,
              "ellipsize" : "end",
              "textColor" : "#333333",
              "maxLines" : 1
            },
            "content" : "我的订单",
            "type" : "text"
          },
          "itemId" : "100505_-_ordercenter",
          "image" : {
            "style" : {
              "darkMode" : "urlAppend",
              "height" : 36,
              "width" : 36,
              "margin" : [
                0,
                15,
                0,
                0
              ]
            },
            "iconUrl" : "https://h5.sinaimg.cn/upload/1014/1355/2022/03/30/myorder.png",
            "type" : "icon"
          },
          "type" : "iconInfo",
          "click" : {
            "type" : "group",
            "modules" : [
              {
                "type" : "scheme",
                "scheme" : "https://m.weibo.cn/c/wbox?id=0tv87kmdt6&page=pages/orderCenter/orderCenter",
                "actionlog" : {
                  "ext" : "moduleId:100505_-_top8|itemId:100505_-_ordercenter",
                  "fid" : "profile_me",
                  "act_code" : 2265,
                  "cardid" : "100505_-_top8"
                }
              },
              {
                "type" : "dot",
                "unreadKey" : "order_gmv"
              }
            ],
            "executeType" : "depend"
          },
          "dot" : {
            "active" : false,
            "style" : {
              "margin" : [
                0,
                0,
                10,
                0
              ],
              "height" : 0,
              "textColorKey" : "CommonButtonText",
              "width" : 0,
              "textSize" : 10,
              "dotColor" : "#F43530",
              "dotColorKey" : "UserProfileCardManagementColor",
              "textColor" : "#FFFFFF"
            },
            "unreadKey" : "order_gmv",
            "inactiveType" : "none",
            "dotText" : "",
            "type" : "dot",
            "activeType" : "dot",
            "dotSource" : "unread"
          }
        },
        {
          "category" : "cell",
          "style" : {
            "margin" : [
              0,
              0,
              0,
              0
            ],
            "grid" : true,
            "height" : 82
          },
          "content" : {
            "style" : {
              "margin" : [
                0,
                6,
                0,
                0
              ],
              "textColorKey" : "CommonGray33",
              "gravity" : "center",
              "textSize" : 12,
              "ellipsize" : "end",
              "textColor" : "#333333",
              "maxLines" : 1
            },
            "content" : "创作中心",
            "type" : "text"
          },
          "itemId" : "100505_-_productcenter",
          "image" : {
            "style" : {
              "darkMode" : "urlAppend",
              "height" : 36,
              "width" : 36,
              "margin" : [
                0,
                15,
                0,
                0
              ]
            },
            "iconUrl" : "https://h5.sinaimg.cn/upload/100/888/2021/07/16/productcenter.png",
            "type" : "icon"
          },
          "type" : "iconInfo",
          "click" : {
            "type" : "group",
            "modules" : [
              {
                "type" : "scheme",
                "scheme" : "https://m.weibo.cn/c/wbox?id=qgb2672tlf&route=center",
                "actionlog" : {
                  "ext" : "moduleId:100505_-_top8|itemId:100505_-_productcenter",
                  "fid" : "profile_me",
                  "act_code" : 2265,
                  "cardid" : "100505_-_top8"
                }
              },
              {
                "type" : "dot",
                "unreadKey" : "productcenter_dot"
              }
            ],
            "executeType" : "depend"
          },
          "dot" : {
            "active" : false,
            "style" : {
              "margin" : [
                0,
                0,
                10,
                0
              ],
              "height" : 0,
              "textColorKey" : "CommonButtonText",
              "width" : 0,
              "textSize" : 10,
              "dotColor" : "#F43530",
              "dotColorKey" : "UserProfileCardManagementColor",
              "textColor" : "#FFFFFF"
            },
            "unreadKey" : "productcenter_dot",
            "inactiveType" : "none",
            "dotText" : "",
            "type" : "dot",
            "activeType" : "dot",
            "dotSource" : "unread"
          }
        },
        {
          "category" : "cell",
          "style" : {
            "margin" : [
              0,
              0,
              0,
              0
            ],
            "grid" : true,
            "height" : 82
          },
          "content" : {
            "style" : {
              "margin" : [
                0,
                6,
                0,
                0
              ],
              "textColorKey" : "CommonGray33",
              "gravity" : "center",
              "textSize" : 12,
              "ellipsize" : "end",
              "textColor" : "#333333",
              "maxLines" : 1
            },
            "content" : "广告中心",
            "type" : "text"
          },
          "itemId" : "100505_-_promote",
          "image" : {
            "style" : {
              "darkMode" : "urlAppend",
              "height" : 36,
              "width" : 36,
              "margin" : [
                0,
                15,
                0,
                0
              ]
            },
            "iconUrl" : "https://h5.sinaimg.cn/upload/100/888/2021/04/01/promote.png",
            "type" : "icon"
          },
          "type" : "iconInfo",
          "click" : {
            "type" : "group",
            "modules" : [
              {
                "type" : "scheme",
                "scheme" : "sinaweibo://browser?topnavstyle=2&immersiveScroll=100&portrait_only=1&url=https%3A%2F%2Ftuiguang-home.biz.weibo.com",
                "actionlog" : {
                  "ext" : "moduleId:100505_-_top8|itemId:100505_-_promote",
                  "fid" : "profile_me",
                  "act_code" : 2265,
                  "cardid" : "100505_-_top8"
                }
              }
            ],
            "executeType" : "depend"
          }
        }
      ],
      "type" : "grid",
      "category" : "group"
    },
    {
      "category" : "group",
      "itemId" : "100505_-_recentlyuser",
      "style" : {
        "contentHeight" : 105,
        "scrollMarginLeft" : 8,
        "scrollMarginRight" : 8,
        "margin" : [
          10,
          10,
          10,
          0
        ],
        "background" : {
          "colorKey" : "CommonCardBackground",
          "type" : "color",
          "corners" : [
            7,
            7,
            7,
            7
          ],
          "color" : "#FFFFFF"
        }
      },
      "header" : {
        "category" : "cell",
        "itemId" : "100505_-_recentlyuser_-_header",
        "style" : {
          "margin" : [
            12,
            0,
            0,
            0
          ],
          "height" : 40
        },
        "content" : {
          "style" : {
            "textColor" : "#939393",
            "textColorKey" : "CommonGray93",
            "ellipsize" : "end",
            "maxLines" : 1,
            "textSize" : 12
          },
          "content" : "查看全部",
          "type" : "text"
        },
        "title" : {
          "style" : {
            "textColor" : "#333333",
            "textColorKey" : "CommonGray33",
            "ellipsize" : "end",
            "maxLines" : 1,
            "textSize" : 14,
            "bold" : true
          },
          "content" : "我的经常访问",
          "type" : "text"
        },
        "type" : "title",
        "click" : {
          "type" : "group",
          "modules" : [
            {
              "actionlog" : {
                "ext" : "moduleId:100505_-_recentlyuser|itemId:100505_-_recentlyuser_-_header",
                "fid" : "profile_me",
                "act_code" : 2265,
                "cardid" : "100505_-_recentlyuser"
              },
              "type" : "scheme",
              "scheme" : "sinaweibo://cardlist?containerid=231093_-_recently&extparam=source_type:profile_me&back_me_refresh=1",
              "params" : {
                "needRefresh" : true
              }
            }
          ],
          "executeType" : "depend"
        },
        "dot" : {
          "active" : false,
          "style" : {
            "margin" : [
              0,
              0,
              10,
              0
            ],
            "height" : 0,
            "textColorKey" : "CommonButtonText",
            "width" : 0,
            "textSize" : 10,
            "dotColor" : "#F43530",
            "dotColorKey" : "UserProfileCardManagementColor",
            "textColor" : "#FFFFFF"
          },
          "unreadKey" : "",
          "iconUrl" : "https://h5.sinaimg.cn/upload/100/888/2021/03/22/jiantouhui.png",
          "inactiveType" : "icon",
          "dotText" : "",
          "type" : "dot",
          "activeType" : "dot",
          "dotSource" : "unread"
        }
      },
      "canEdit" : "1",
      "type" : "horizontal",
      "items" : [
        {
          "category" : "cell",
          "style" : {
            "grid" : true,
            "width" : 66,
            "height" : 105
          },
          "avatar" : {
            "style" : {
              "height" : 58,
              "margin" : [
                0,
                6,
                0,
                0
              ],
              "vIconWidth" : 16,
              "pendantWidth" : 10,
              "pendantOffsetX" : 23,
              "width" : 58,
              "pendantHeight" : 10,
              "pendantOffsetY" : -23,
              "pendantDarkMode" : "urlAppend"
            },
            "type" : "avatar",
            "badgeUrl" : "https://h5.sinaimg.cn/upload/100/888/2021/04/07/avatar_vip_golden.png",
            "avatarUrl" : "https://tvax1.sinaimg.cn/crop.0.16.718.718.180/006W9z2kly8fizpxrkhzyj30jy0kvgmz.jpg?KID=imgbed,tva&Expires=1684229832&ssig=moXwV6WPA%2F"
          },
          "content" : {
            "type" : "text",
            "style" : {
              "margin" : [
                1,
                9,
                1,
                0
              ],
              "textColorKey" : "CommonGray33",
              "gravity" : "center",
              "textSize" : 13,
              "ellipsize" : "end",
              "textColor" : "#333333",
              "maxLines" : 1
            },
            "content" : "星赏一下"
          },
          "itemId" : "100505_-_recentlyuser_-_body_-_1005051001_0_57.1_0_6356104116",
          "type" : "avatarInfo",
          "click" : {
            "type" : "group",
            "modules" : [
              {
                "type" : "scheme",
                "scheme" : "sinaweibo://userinfo?lcardid=100505_-_recentlyuser&uid=6356104116",
                "actionlog" : {
                  "ext" : "moduleId:100505_-_recentlyuser|itemId:100505_-_recentlyuser_-_body_-_1005051001_0_57.1_0_6356104116",
                  "fid" : "profile_me",
                  "act_code" : 2265,
                  "cardid" : "100505_-_recentlyuser"
                }
              }
            ],
            "executeType" : "depend"
          }
        },
        {
          "category" : "cell",
          "style" : {
            "grid" : true,
            "width" : 66,
            "height" : 105
          },
          "avatar" : {
            "style" : {
              "height" : 58,
              "margin" : [
                0,
                6,
                0,
                0
              ],
              "vIconWidth" : 16,
              "pendantWidth" : 10,
              "pendantOffsetX" : 23,
              "width" : 58,
              "pendantHeight" : 10,
              "pendantOffsetY" : -23,
              "pendantDarkMode" : "urlAppend"
            },
            "type" : "avatar",
            "badgeUrl" : "https://h5.sinaimg.cn/upload/100/888/2021/04/07/avatar_vip_golden.png",
            "avatarUrl" : "https://tva3.sinaimg.cn/crop.0.0.180.180.180/66fd066bjw1e8qgp5bmzyj2050050aa8.jpg?KID=imgbed,tva&Expires=1684229832&ssig=ccbYIVK0xb"
          },
          "content" : {
            "type" : "text",
            "style" : {
              "margin" : [
                1,
                9,
                1,
                0
              ],
              "textColorKey" : "CommonGray33",
              "gravity" : "center",
              "textSize" : 13,
              "ellipsize" : "end",
              "textColor" : "#333333",
              "maxLines" : 1
            },
            "content" : "宝玉xp"
          },
          "itemId" : "100505_-_recentlyuser_-_body_-_1005051001_0_57.1_0_1727858283",
          "type" : "avatarInfo",
          "click" : {
            "type" : "group",
            "modules" : [
              {
                "type" : "scheme",
                "scheme" : "sinaweibo://userinfo?lcardid=100505_-_recentlyuser&uid=1727858283",
                "actionlog" : {
                  "ext" : "moduleId:100505_-_recentlyuser|itemId:100505_-_recentlyuser_-_body_-_1005051001_0_57.1_0_1727858283",
                  "fid" : "profile_me",
                  "act_code" : 2265,
                  "cardid" : "100505_-_recentlyuser"
                }
              }
            ],
            "executeType" : "depend"
          }
        },
        {
          "category" : "cell",
          "style" : {
            "grid" : true,
            "width" : 66,
            "height" : 105
          },
          "avatar" : {
            "style" : {
              "height" : 58,
              "margin" : [
                0,
                6,
                0,
                0
              ],
              "vIconWidth" : 16,
              "pendantWidth" : 10,
              "pendantOffsetX" : 23,
              "width" : 58,
              "pendantHeight" : 10,
              "pendantOffsetY" : -23,
              "pendantDarkMode" : "urlAppend"
            },
            "type" : "avatar",
            "badgeUrl" : "",
            "avatarUrl" : "https://tvax1.sinaimg.cn/crop.0.0.1002.1002.180/006Ln2fBly8gq7qzecstcj30ru0ruwgi.jpg?KID=imgbed,tva&Expires=1684229832&ssig=kVlMEGZioH"
          },
          "content" : {
            "type" : "text",
            "style" : {
              "margin" : [
                1,
                9,
                1,
                0
              ],
              "textColorKey" : "CommonGray33",
              "gravity" : "center",
              "textSize" : 13,
              "ellipsize" : "end",
              "textColor" : "#333333",
              "maxLines" : 1
            },
            "content" : "京那场花雨29180"
          },
          "itemId" : "100505_-_recentlyuser_-_body_-_1005051001_0_57.1_0_6196774983",
          "type" : "avatarInfo",
          "click" : {
            "type" : "group",
            "modules" : [
              {
                "type" : "scheme",
                "scheme" : "sinaweibo://userinfo?lcardid=100505_-_recentlyuser&uid=6196774983",
                "actionlog" : {
                  "ext" : "moduleId:100505_-_recentlyuser|itemId:100505_-_recentlyuser_-_body_-_1005051001_0_57.1_0_6196774983",
                  "fid" : "profile_me",
                  "act_code" : 2265,
                  "cardid" : "100505_-_recentlyuser"
                }
              }
            ],
            "executeType" : "depend"
          }
        },
        {
          "category" : "cell",
          "style" : {
            "grid" : true,
            "width" : 66,
            "height" : 105
          },
          "avatar" : {
            "pendantUrl" : "https://h5.sinaimg.cn/upload/1014/1355/2022/06/10/reddot.png",
            "style" : {
              "height" : 58,
              "margin" : [
                0,
                6,
                0,
                0
              ],
              "vIconWidth" : 16,
              "pendantWidth" : 10,
              "pendantOffsetX" : 23,
              "width" : 58,
              "pendantHeight" : 10,
              "pendantOffsetY" : -23,
              "pendantDarkMode" : "urlAppend"
            },
            "type" : "avatar",
            "badgeUrl" : "https://h5.sinaimg.cn/upload/100/888/2021/04/07/avatar_vip_golden.png",
            "avatarUrl" : "https://tvax3.sinaimg.cn/crop.0.0.1080.1080.180/007gynYJly8hcxd8yljwqj30u00u0wfo.jpg?KID=imgbed,tva&Expires=1684229832&ssig=UhQavDV%2Fg9"
          },
          "content" : {
            "type" : "text",
            "style" : {
              "margin" : [
                1,
                9,
                1,
                0
              ],
              "textColorKey" : "CommonGray33",
              "gravity" : "center",
              "textSize" : 13,
              "ellipsize" : "end",
              "textColor" : "#333333",
              "maxLines" : 1
            },
            "content" : "底射底射"
          },
          "itemId" : "100505_-_recentlyuser_-_body_-_1005051001_0_57.1_0_6657546529",
          "type" : "avatarInfo",
          "click" : {
            "type" : "group",
            "modules" : [
              {
                "actionlog" : {
                  "ext" : "moduleId:100505_-_recentlyuser|itemId:100505_-_recentlyuser_-_body_-_1005051001_0_57.1_0_6657546529",
                  "fid" : "profile_me",
                  "act_code" : 2265,
                  "cardid" : "100505_-_recentlyuser"
                },
                "type" : "scheme",
                "scheme" : "sinaweibo://userinfo?lcardid=100505_-_recentlyuser&uid=6657546529&back_me_refresh=1",
                "params" : {
                  "needRefresh" : true
                }
              }
            ],
            "executeType" : "depend"
          }
        },
        {
          "category" : "cell",
          "style" : {
            "grid" : true,
            "width" : 66,
            "height" : 105
          },
          "avatar" : {
            "pendantUrl" : "https://h5.sinaimg.cn/upload/1014/1355/2022/06/10/reddot.png",
            "style" : {
              "height" : 58,
              "margin" : [
                0,
                6,
                0,
                0
              ],
              "vIconWidth" : 16,
              "pendantWidth" : 10,
              "pendantOffsetX" : 23,
              "width" : 58,
              "pendantHeight" : 10,
              "pendantOffsetY" : -23,
              "pendantDarkMode" : "urlAppend"
            },
            "type" : "avatar",
            "badgeUrl" : "https://h5.sinaimg.cn/upload/100/888/2021/04/07/avatar_vip_golden.png",
            "avatarUrl" : "https://tvax1.sinaimg.cn/crop.0.0.1080.1080.180/005ZwWLZly8hd82pa1ek1j30u00u0jtw.jpg?KID=imgbed,tva&Expires=1684229832&ssig=cWIs%2FWbBNo"
          },
          "content" : {
            "type" : "text",
            "style" : {
              "margin" : [
                1,
                9,
                1,
                0
              ],
              "textColorKey" : "CommonGray33",
              "gravity" : "center",
              "textSize" : 13,
              "ellipsize" : "end",
              "textColor" : "#333333",
              "maxLines" : 1
            },
            "content" : "先锋大队长的后腿"
          },
          "itemId" : "100505_-_recentlyuser_-_body_-_1005051001_0_57.1_0_5489873079",
          "type" : "avatarInfo",
          "click" : {
            "type" : "group",
            "modules" : [
              {
                "actionlog" : {
                  "ext" : "moduleId:100505_-_recentlyuser|itemId:100505_-_recentlyuser_-_body_-_1005051001_0_57.1_0_5489873079",
                  "fid" : "profile_me",
                  "act_code" : 2265,
                  "cardid" : "100505_-_recentlyuser"
                },
                "type" : "scheme",
                "scheme" : "sinaweibo://userinfo?lcardid=100505_-_recentlyuser&uid=5489873079&back_me_refresh=1",
                "params" : {
                  "needRefresh" : true
                }
              }
            ],
            "executeType" : "depend"
          }
        },
        {
          "category" : "cell",
          "style" : {
            "grid" : true,
            "width" : 66,
            "height" : 105
          },
          "avatar" : {
            "style" : {
              "height" : 58,
              "margin" : [
                0,
                6,
                0,
                0
              ],
              "vIconWidth" : 16,
              "pendantWidth" : 10,
              "pendantOffsetX" : 23,
              "width" : 58,
              "pendantHeight" : 10,
              "pendantOffsetY" : -23,
              "pendantDarkMode" : "urlAppend"
            },
            "type" : "avatar",
            "badgeUrl" : "https://h5.sinaimg.cn/upload/100/888/2021/04/07/avatar_vip_golden.png",
            "avatarUrl" : "https://tvax1.sinaimg.cn/crop.0.0.281.281.180/6ca72b22ly8hbbcfd61h5j207t07taa2.jpg?KID=imgbed,tva&Expires=1684229832&ssig=BG2sDIfp9%2B"
          },
          "content" : {
            "type" : "text",
            "style" : {
              "margin" : [
                1,
                9,
                1,
                0
              ],
              "textColorKey" : "CommonGray33",
              "gravity" : "center",
              "textSize" : 13,
              "ellipsize" : "end",
              "textColor" : "#333333",
              "maxLines" : 1
            },
            "content" : "极速拍档-小乔"
          },
          "itemId" : "100505_-_recentlyuser_-_body_-_1005051001_0_57.1_0_1822894882",
          "type" : "avatarInfo",
          "click" : {
            "type" : "group",
            "modules" : [
              {
                "type" : "scheme",
                "scheme" : "sinaweibo://userinfo?lcardid=100505_-_recentlyuser&uid=1822894882",
                "actionlog" : {
                  "ext" : "moduleId:100505_-_recentlyuser|itemId:100505_-_recentlyuser_-_body_-_1005051001_0_57.1_0_1822894882",
                  "fid" : "profile_me",
                  "act_code" : 2265,
                  "cardid" : "100505_-_recentlyuser"
                }
              }
            ],
            "executeType" : "depend"
          }
        },
        {
          "category" : "cell",
          "style" : {
            "grid" : true,
            "width" : 66,
            "height" : 105
          },
          "avatar" : {
            "style" : {
              "height" : 58,
              "margin" : [
                0,
                6,
                0,
                0
              ],
              "vIconWidth" : 16,
              "pendantWidth" : 10,
              "pendantOffsetX" : 23,
              "width" : 58,
              "pendantHeight" : 10,
              "pendantOffsetY" : -23,
              "pendantDarkMode" : "urlAppend"
            },
            "type" : "avatar",
            "badgeUrl" : "https://h5.sinaimg.cn/upload/100/888/2021/04/07/avatar_vip_golden.png",
            "avatarUrl" : "https://tvax2.sinaimg.cn/crop.0.0.1080.1080.180/9fa39989ly8hcs3ovuijmj20u00u0q47.jpg?KID=imgbed,tva&Expires=1684229832&ssig=Vv9ikAVCwe"
          },
          "content" : {
            "type" : "text",
            "style" : {
              "margin" : [
                1,
                9,
                1,
                0
              ],
              "textColorKey" : "CommonGray33",
              "gravity" : "center",
              "textSize" : 13,
              "ellipsize" : "end",
              "textColor" : "#333333",
              "maxLines" : 1
            },
            "content" : "灵儿chili"
          },
          "itemId" : "100505_-_recentlyuser_-_body_-_1005051001_0_57.1_0_2678299017",
          "type" : "avatarInfo",
          "click" : {
            "type" : "group",
            "modules" : [
              {
                "type" : "scheme",
                "scheme" : "sinaweibo://userinfo?lcardid=100505_-_recentlyuser&uid=2678299017",
                "actionlog" : {
                  "ext" : "moduleId:100505_-_recentlyuser|itemId:100505_-_recentlyuser_-_body_-_1005051001_0_57.1_0_2678299017",
                  "fid" : "profile_me",
                  "act_code" : 2265,
                  "cardid" : "100505_-_recentlyuser"
                }
              }
            ],
            "executeType" : "depend"
          }
        },
        {
          "category" : "cell",
          "style" : {
            "grid" : true,
            "width" : 66,
            "height" : 105
          },
          "avatar" : {
            "style" : {
              "height" : 58,
              "margin" : [
                0,
                6,
                0,
                0
              ],
              "vIconWidth" : 16,
              "pendantWidth" : 10,
              "pendantOffsetX" : 23,
              "width" : 58,
              "pendantHeight" : 10,
              "pendantOffsetY" : -23,
              "pendantDarkMode" : "urlAppend"
            },
            "type" : "avatar",
            "badgeUrl" : "https://h5.sinaimg.cn/upload/100/888/2021/04/07/avatar_vip_golden.png",
            "avatarUrl" : "https://tvax3.sinaimg.cn/crop.0.0.1080.1080.180/69ada427ly8hbzrbw29edj20u00u0gni.jpg?KID=imgbed,tva&Expires=1684229832&ssig=aU4FS7Pl2w"
          },
          "content" : {
            "type" : "text",
            "style" : {
              "margin" : [
                1,
                9,
                1,
                0
              ],
              "textColorKey" : "CommonGray33",
              "gravity" : "center",
              "textSize" : 13,
              "ellipsize" : "end",
              "textColor" : "#333333",
              "maxLines" : 1
            },
            "content" : "解说小鹿"
          },
          "itemId" : "100505_-_recentlyuser_-_body_-_1005051001_0_57.1_0_1772987431",
          "type" : "avatarInfo",
          "click" : {
            "type" : "group",
            "modules" : [
              {
                "type" : "scheme",
                "scheme" : "sinaweibo://userinfo?lcardid=100505_-_recentlyuser&uid=1772987431",
                "actionlog" : {
                  "ext" : "moduleId:100505_-_recentlyuser|itemId:100505_-_recentlyuser_-_body_-_1005051001_0_57.1_0_1772987431",
                  "fid" : "profile_me",
                  "act_code" : 2265,
                  "cardid" : "100505_-_recentlyuser"
                }
              }
            ],
            "executeType" : "depend"
          }
        },
        {
          "category" : "cell",
          "style" : {
            "grid" : true,
            "width" : 66,
            "height" : 105
          },
          "avatar" : {
            "style" : {
              "height" : 58,
              "margin" : [
                0,
                6,
                0,
                0
              ],
              "vIconWidth" : 16,
              "pendantWidth" : 10,
              "pendantOffsetX" : 23,
              "width" : 58,
              "pendantHeight" : 10,
              "pendantOffsetY" : -23,
              "pendantDarkMode" : "urlAppend"
            },
            "type" : "avatar",
            "badgeUrl" : "",
            "avatarUrl" : "https://tvax3.sinaimg.cn/crop.0.393.1786.1786.180/51061952ly8fwijboxum9j21ea1okdyc.jpg?KID=imgbed,tva&Expires=1684229832&ssig=%2FRxNcTGzNi"
          },
          "content" : {
            "type" : "text",
            "style" : {
              "margin" : [
                1,
                9,
                1,
                0
              ],
              "textColorKey" : "CommonGray33",
              "gravity" : "center",
              "textSize" : 13,
              "ellipsize" : "end",
              "textColor" : "#333333",
              "maxLines" : 1
            },
            "content" : "明星大长腿"
          },
          "itemId" : "100505_-_recentlyuser_-_body_-_1005051001_0_57.1_0_1359354194",
          "type" : "avatarInfo",
          "click" : {
            "type" : "group",
            "modules" : [
              {
                "type" : "scheme",
                "scheme" : "sinaweibo://userinfo?lcardid=100505_-_recentlyuser&uid=1359354194",
                "actionlog" : {
                  "ext" : "moduleId:100505_-_recentlyuser|itemId:100505_-_recentlyuser_-_body_-_1005051001_0_57.1_0_1359354194",
                  "fid" : "profile_me",
                  "act_code" : 2265,
                  "cardid" : "100505_-_recentlyuser"
                }
              }
            ],
            "executeType" : "depend"
          }
        },
        {
          "category" : "cell",
          "style" : {
            "grid" : true,
            "width" : 66,
            "height" : 105
          },
          "avatar" : {
            "pendantUrl" : "https://h5.sinaimg.cn/upload/1014/1355/2022/06/10/reddot.png",
            "style" : {
              "height" : 58,
              "margin" : [
                0,
                6,
                0,
                0
              ],
              "vIconWidth" : 16,
              "pendantWidth" : 10,
              "pendantOffsetX" : 23,
              "width" : 58,
              "pendantHeight" : 10,
              "pendantOffsetY" : -23,
              "pendantDarkMode" : "urlAppend"
            },
            "type" : "avatar",
            "badgeUrl" : "https://h5.sinaimg.cn/upload/100/888/2021/04/07/Vip.png",
            "avatarUrl" : "https://tvax3.sinaimg.cn/crop.0.0.1080.1080.180/8f8ff723ly8hc543ycjl4j20u00u0gnl.jpg?KID=imgbed,tva&Expires=1684229832&ssig=Gd%2FLob%2BOaG"
          },
          "content" : {
            "type" : "text",
            "style" : {
              "margin" : [
                1,
                9,
                1,
                0
              ],
              "textColorKey" : "CommonGray33",
              "gravity" : "center",
              "textSize" : 13,
              "ellipsize" : "end",
              "textColor" : "#333333",
              "maxLines" : 1
            },
            "content" : "青楼煮酒读春秋赏月话风流"
          },
          "itemId" : "100505_-_recentlyuser_-_body_-_1005051001_0_57.1_0_2408576803",
          "type" : "avatarInfo",
          "click" : {
            "type" : "group",
            "modules" : [
              {
                "actionlog" : {
                  "ext" : "moduleId:100505_-_recentlyuser|itemId:100505_-_recentlyuser_-_body_-_1005051001_0_57.1_0_2408576803",
                  "fid" : "profile_me",
                  "act_code" : 2265,
                  "cardid" : "100505_-_recentlyuser"
                },
                "type" : "scheme",
                "scheme" : "sinaweibo://userinfo?lcardid=100505_-_recentlyuser&uid=2408576803&back_me_refresh=1",
                "params" : {
                  "needRefresh" : true
                }
              }
            ],
            "executeType" : "depend"
          }
        }
      ]
    }
  ],
  "mineinfo" : {
    "navgationScheme" : "https://m.weibo.cn/z/recommend/entrance?showmenu=0&luicode=10000011",
    "screen_name" : "废话GPT",
    "uid" : "3934103603",
    "launchScheme" : "",
    "containerid" : ""
  }
}
